{"inputs":{"package.json":{"bytes":578,"imports":[]},"node_modules/.pnpm/svelte@3.55.1/node_modules/svelte/internal/index.mjs":{"bytes":78599,"imports":[],"format":"esm"},"node_modules/.pnpm/svelte@3.55.1/node_modules/svelte/store/index.mjs":{"bytes":3174,"imports":[{"path":"node_modules/.pnpm/svelte@3.55.1/node_modules/svelte/internal/index.mjs","kind":"import-statement","original":"../internal/index.mjs"},{"path":"node_modules/.pnpm/svelte@3.55.1/node_modules/svelte/internal/index.mjs","kind":"import-statement","original":"../internal/index.mjs"}],"format":"esm"},"src/lib/utils.ts":{"bytes":362,"imports":[],"format":"esm"},"src/lib/stores/game.ts":{"bytes":1821,"imports":[{"path":"node_modules/.pnpm/svelte@3.55.1/node_modules/svelte/store/index.mjs","kind":"import-statement","original":"svelte/store"},{"path":"src/lib/stores/figure.ts","kind":"import-statement","original":"./figure"},{"path":"src/lib/stores/heap.ts","kind":"import-statement","original":"./heap"},{"path":"src/lib/utils.ts","kind":"import-statement","original":"$lib/utils"}],"format":"esm"},"src/lib/stores/heap.ts":{"bytes":1783,"imports":[{"path":"node_modules/.pnpm/svelte@3.55.1/node_modules/svelte/store/index.mjs","kind":"import-statement","original":"svelte/store"},{"path":"src/lib/utils.ts","kind":"import-statement","original":"$lib/utils"},{"path":"src/lib/stores/game.ts","kind":"import-statement","original":"./game"}],"format":"esm"},"src/lib/stores/figure.ts":{"bytes":2875,"imports":[{"path":"node_modules/.pnpm/svelte@3.55.1/node_modules/svelte/store/index.mjs","kind":"import-statement","original":"svelte/store"},{"path":"src/lib/utils.ts","kind":"import-statement","original":"$lib/utils"},{"path":"src/lib/stores/heap.ts","kind":"import-statement","original":"./heap"},{"path":"src/lib/stores/game.ts","kind":"import-statement","original":"./game"}],"format":"esm"},"src/lib/components/Nav.svelte":{"bytes":13520,"imports":[{"path":"node_modules/.pnpm/svelte@3.55.1/node_modules/svelte/internal/index.mjs","kind":"import-statement","original":"svelte/internal"},{"path":"src/lib/stores/figure.ts","kind":"import-statement","original":"$lib/stores/figure"},{"path":"src/lib/stores/game.ts","kind":"import-statement","original":"$lib/stores/game"}],"format":"esm"},"src/lib/components/Pixel.svelte":{"bytes":2856,"imports":[{"path":"node_modules/.pnpm/svelte@3.55.1/node_modules/svelte/internal/index.mjs","kind":"import-statement","original":"svelte/internal"},{"path":"src/lib/utils.ts","kind":"import-statement","original":"$lib/utils"}],"format":"esm"},"src/lib/actions/controls.ts":{"bytes":2086,"imports":[{"path":"src/lib/stores/game.ts","kind":"import-statement","original":"$lib/stores/game"},{"path":"src/lib/stores/figure.ts","kind":"import-statement","original":"$lib/stores/figure"},{"path":"src/lib/utils.ts","kind":"import-statement","original":"$lib/utils"}],"format":"esm"},"src/lib/components/Board.svelte":{"bytes":9182,"imports":[{"path":"node_modules/.pnpm/svelte@3.55.1/node_modules/svelte/internal/index.mjs","kind":"import-statement","original":"svelte/internal"},{"path":"src/lib/components/Pixel.svelte","kind":"import-statement","original":"./Pixel.svelte"},{"path":"src/lib/actions/controls.ts","kind":"import-statement","original":"$lib/actions/controls"},{"path":"src/lib/stores/figure.ts","kind":"import-statement","original":"$lib/stores/figure"},{"path":"src/lib/stores/heap.ts","kind":"import-statement","original":"$lib/stores/heap"},{"path":"src/lib/stores/game.ts","kind":"import-statement","original":"$lib/stores/game"}],"format":"esm"},"src/svg/gh.svg":{"bytes":825,"imports":[]},"src/lib/components/Score.svelte":{"bytes":3944,"imports":[{"path":"node_modules/.pnpm/svelte@3.55.1/node_modules/svelte/internal/index.mjs","kind":"import-statement","original":"svelte/internal"},{"path":"src/svg/gh.svg","kind":"import-statement","original":"$svg/gh.svg"},{"path":"src/lib/stores/game.ts","kind":"import-statement","original":"$lib/stores/game"}],"format":"esm"},"src/css/theme.css":{"bytes":606,"imports":[{"path":"https://fonts.googleapis.com/css2?family=Silkscreen:wght@400;700&display=swap","kind":"import-rule","external":true}]},"src/css/base.css":{"bytes":1033,"imports":[]},"src/css/board.css":{"bytes":307,"imports":[]},"src/css/pixel.css":{"bytes":147,"imports":[]},"src/css/nav.css":{"bytes":1277,"imports":[{"path":"data:image/svg+xml;charset=utf8,%3Csvg%20xmlns='http://www.w3.org/2000/svg'%20viewBox='0%200%204%205'%3E%3Cpath%20fill='currentColor'%20d='M2%200L0%202h4zm0%205L0%203h4z'/%3E%3C/svg%3E","kind":"url-token","external":true}]},"src/app.css":{"bytes":121,"imports":[{"path":"src/css/theme.css","kind":"import-rule","original":"css/theme.css"},{"path":"src/css/base.css","kind":"import-rule","original":"css/base.css"},{"path":"src/css/board.css","kind":"import-rule","original":"css/board.css"},{"path":"src/css/pixel.css","kind":"import-rule","original":"css/pixel.css"},{"path":"src/css/nav.css","kind":"import-rule","original":"css/nav.css"}]},"fakecss:/Users/valexr/Desktop/Tetrix/src/App.esbuild-svelte-fake-css":{"bytes":225,"imports":[{"path":"src/app.css","kind":"import-rule","original":"app.css"}]},"src/App.svelte":{"bytes":4040,"imports":[{"path":"node_modules/.pnpm/svelte@3.55.1/node_modules/svelte/internal/index.mjs","kind":"import-statement","original":"svelte/internal"},{"path":"src/lib/components/Nav.svelte","kind":"import-statement","original":"$lib/components/Nav.svelte"},{"path":"src/lib/components/Board.svelte","kind":"import-statement","original":"$lib/components/Board.svelte"},{"path":"src/lib/components/Score.svelte","kind":"import-statement","original":"$lib/components/Score.svelte"},{"path":"fakecss:/Users/valexr/Desktop/Tetrix/src/App.esbuild-svelte-fake-css","kind":"import-statement","original":"/Users/valexr/Desktop/Tetrix/src/App.esbuild-svelte-fake-css"}],"format":"esm"},"src/app.ts":{"bytes":184,"imports":[{"path":"package.json","kind":"import-statement","original":"package.json"},{"path":"src/App.svelte","kind":"import-statement","original":"./App.svelte"}],"format":"esm"}},"outputs":{"public/build/app.js":{"imports":[],"exports":["default"],"entryPoint":"src/app.ts","cssBundle":"public/build/app.css","inputs":{"package.json":{"bytesInOutput":75},"node_modules/.pnpm/svelte@3.55.1/node_modules/svelte/internal/index.mjs":{"bytesInOutput":4733},"node_modules/.pnpm/svelte@3.55.1/node_modules/svelte/store/index.mjs":{"bytesInOutput":417},"src/lib/utils.ts":{"bytesInOutput":146},"src/lib/stores/game.ts":{"bytesInOutput":738},"src/lib/stores/heap.ts":{"bytesInOutput":528},"src/lib/stores/figure.ts":{"bytesInOutput":1050},"src/lib/components/Nav.svelte":{"bytesInOutput":2869},"src/lib/components/Pixel.svelte":{"bytesInOutput":567},"src/lib/actions/controls.ts":{"bytesInOutput":823},"src/lib/components/Board.svelte":{"bytesInOutput":2117},"src/svg/gh.svg":{"bytesInOutput":835},"src/lib/components/Score.svelte":{"bytesInOutput":831},"fakecss:/Users/valexr/Desktop/Tetrix/src/App.esbuild-svelte-fake-css":{"bytesInOutput":0},"src/App.svelte":{"bytesInOutput":822},"src/app.ts":{"bytesInOutput":74}},"bytes":16648},"public/build/app.css":{"imports":[{"path":"https://fonts.googleapis.com/css2?family=Silkscreen:wght@400;700&display=swap","kind":"import-rule","external":true},{"path":"data:image/svg+xml;charset=utf8,%3Csvg%20xmlns='http://www.w3.org/2000/svg'%20viewBox='0%200%204%205'%3E%3Cpath%20fill='currentColor'%20d='M2%200L0%202h4zm0%205L0%203h4z'/%3E%3C/svg%3E","kind":"url-token","external":true}],"inputs":{"src/css/theme.css":{"bytesInOutput":388},"src/css/base.css":{"bytesInOutput":772},"src/css/board.css":{"bytesInOutput":232},"src/css/pixel.css":{"bytesInOutput":115},"src/css/nav.css":{"bytesInOutput":990},"src/app.css":{"bytesInOutput":0},"fakecss:/Users/valexr/Desktop/Tetrix/src/App.esbuild-svelte-fake-css":{"bytesInOutput":0}},"bytes":2585}}}